Topsis/__init__.py
Topsis/main.py
Topsis101703436-1.0.1.dist-info/LICENSE
Topsis101703436-1.0.1.dist-info/METADATA
Topsis101703436-1.0.1.dist-info/WHEEL
Topsis101703436-1.0.1.dist-info/entry_points.txt
Topsis101703436-1.0.1.dist-info/top_level.txt
Topsis101703436-1.0.1.dist-info/RECORD
