Metadata-Version: 2.1
Name: Topsis101703436
Version: 1.0.1
Summary: UCS633 Assignment - Topsis
Home-page: UNKNOWN
Author: Ranveer Singh
Author-email: donotreply@gmail.com
License: MIT
Keywords: thapar ucs633 assignment majboori
Platform: UNKNOWN
